{"client":"Thunder Client","collectionName":"driven-pass","dateExported":"2022-07-18T19:35:27.185Z","version":"1.1","folders":[{"_id":"369c9807-6ce9-4b19-abad-fc4037295331","name":"config","containerId":"","created":"2022-07-15T20:15:07.942Z","sortNum":2500},{"_id":"4d91744f-e457-434c-8db7-85f7769b71ad","name":"signUp","containerId":"","created":"2022-07-15T20:15:07.943Z","sortNum":5000},{"_id":"b31ff388-50d7-497c-bb35-4a4f0d39ab6a","name":"signIn","containerId":"","created":"2022-07-15T20:15:07.944Z","sortNum":10000},{"_id":"1aaba2c0-caff-4706-9e8a-b0c955fd0c4a","name":"credentials","containerId":"","created":"2022-07-15T20:15:07.945Z","sortNum":20000,"settings":{"headers":[{"name":"Authorization","value":"Bearer {{token}}"}],"tests":[]}},{"_id":"be220905-a52e-4f8e-bdb1-f858367a7939","name":"config","containerId":"1aaba2c0-caff-4706-9e8a-b0c955fd0c4a","created":"2022-07-15T20:15:55.455Z","sortNum":20000},{"_id":"2785ec35-c5af-4137-b505-a918e6fd0711","name":"config","containerId":"3d721995-cf4e-435d-9d58-ce01c61a7f2a","created":"2022-07-15T20:23:16.863Z","sortNum":20000},{"_id":"e015dd07-2069-4dde-a053-641aa9094b3f","name":"config","containerId":"572d22a9-76f3-4be7-bbbb-c16d9a3ef66f","created":"2022-07-18T11:13:54.539Z","sortNum":20000},{"_id":"d52b560e-ae38-4ae6-bb1c-66e303974e5a","name":"config","containerId":"9c4d317c-9132-4371-abef-7ebf7d7f0b8b","created":"2022-07-18T17:15:30.224Z","sortNum":20000},{"_id":"3d721995-cf4e-435d-9d58-ce01c61a7f2a","name":"secureNote","containerId":"","created":"2022-07-15T20:23:16.860Z","sortNum":30000,"settings":{"headers":[{"name":"Authorization","value":"Bearer {{token}}"}],"tests":[]}},{"_id":"53696c3e-110a-42fb-91fa-b84cd9f19107","name":"create","containerId":"1aaba2c0-caff-4706-9e8a-b0c955fd0c4a","created":"2022-07-15T20:15:07.947Z","sortNum":40000},{"_id":"3ad2ce09-9415-4bce-91c0-81461384e3f9","name":"create","containerId":"3d721995-cf4e-435d-9d58-ce01c61a7f2a","created":"2022-07-15T20:23:16.864Z","sortNum":40000},{"_id":"572d22a9-76f3-4be7-bbbb-c16d9a3ef66f","name":"cards","containerId":"","created":"2022-07-18T11:13:54.537Z","sortNum":40000,"settings":{"headers":[{"name":"Authorization","value":"Bearer {{token}}"}],"tests":[]}},{"_id":"068d8990-a032-4d5e-bf2f-5883afec2bb4","name":"create","containerId":"572d22a9-76f3-4be7-bbbb-c16d9a3ef66f","created":"2022-07-18T11:13:54.540Z","sortNum":40000},{"_id":"3532d702-468f-408f-ba91-84da5aded2a2","name":"create","containerId":"9c4d317c-9132-4371-abef-7ebf7d7f0b8b","created":"2022-07-18T17:15:30.225Z","sortNum":40000},{"_id":"42f703fd-12d1-4ff1-8c0b-4a5f9b44b7ab","name":"findOneOrMany","containerId":"1aaba2c0-caff-4706-9e8a-b0c955fd0c4a","created":"2022-07-15T20:15:07.949Z","sortNum":50000},{"_id":"f5769f4d-65e2-4c8c-a66a-5d4b7e362a0e","name":"findOneOrMany","containerId":"3d721995-cf4e-435d-9d58-ce01c61a7f2a","created":"2022-07-15T20:23:16.866Z","sortNum":50000},{"_id":"8bbeeea9-f051-434a-ab2f-ef00c8999595","name":"findOneOrMany","containerId":"572d22a9-76f3-4be7-bbbb-c16d9a3ef66f","created":"2022-07-18T11:13:54.543Z","sortNum":50000},{"_id":"9c4d317c-9132-4371-abef-7ebf7d7f0b8b","name":"wifi","containerId":"","created":"2022-07-18T17:15:30.223Z","sortNum":50000,"settings":{"headers":[{"name":"Authorization","value":"Bearer {{token}}"}],"tests":[]}},{"_id":"bcf4a36b-349d-443f-ad51-c526e806732c","name":"findOneOrMany","containerId":"9c4d317c-9132-4371-abef-7ebf7d7f0b8b","created":"2022-07-18T17:15:30.227Z","sortNum":50000},{"_id":"dcab6444-45f3-46e9-8749-4b17e3188706","name":"delete","containerId":"1aaba2c0-caff-4706-9e8a-b0c955fd0c4a","created":"2022-07-15T20:15:07.951Z","sortNum":60000},{"_id":"12587671-fc1a-42eb-9a77-13a69c4893d8","name":"delete","containerId":"3d721995-cf4e-435d-9d58-ce01c61a7f2a","created":"2022-07-15T20:23:16.867Z","sortNum":60000},{"_id":"f2e6b1f0-b0a0-47f5-bcd3-6eba666ebf1b","name":"delete","containerId":"572d22a9-76f3-4be7-bbbb-c16d9a3ef66f","created":"2022-07-18T11:13:54.545Z","sortNum":60000},{"_id":"b50f57b4-d339-4589-b8d5-e8d9fc6f1913","name":"delete","containerId":"9c4d317c-9132-4371-abef-7ebf7d7f0b8b","created":"2022-07-18T17:15:30.228Z","sortNum":60000}],"requests":[{"_id":"25610a7b-f306-4d21-b400-c10d17229e29","colId":"1e431bf5-dd3f-4be4-8d48-fa10fb4a1480","containerId":"4d91744f-e457-434c-8db7-85f7769b71ad","name":"sign-up-201","url":"{{apiUrl}}/sign-up","method":"POST","sortNum":10000,"created":"2022-07-15T20:15:07.943Z","modified":"2022-07-15T20:15:07.943Z","headers":[],"params":[],"body":{"type":"json","raw":"{\n  \"email\": \"{{email}}\",\n  \"password\": \"{{password}}\"\n}","form":[]},"tests":[{"type":"res-code","custom":"","action":"equal","value":"201"}]},{"_id":"1765e556-d625-4866-ac0c-b7f62ddbe3ec","colId":"1e431bf5-dd3f-4be4-8d48-fa10fb4a1480","containerId":"b31ff388-50d7-497c-bb35-4a4f0d39ab6a","name":"sign-in-200","url":"{{apiUrl}}/sign-in","method":"POST","sortNum":10000,"created":"2022-07-15T20:15:07.944Z","modified":"2022-07-15T20:15:07.944Z","headers":[],"params":[],"body":{"type":"json","raw":"{\n  \"email\": \"{{email}}\",\n  \"password\": \"{{password}}\"\n}","form":[]},"tests":[{"type":"res-code","custom":"","action":"equal","value":"200"},{"type":"res-body","custom":"","action":"isjson","value":""},{"type":"set-env-var","custom":"json.token","action":"setto","value":"{{token}}"}]},{"_id":"8bf079f7-8d7e-4db7-9204-9a0cda074935","colId":"1e431bf5-dd3f-4be4-8d48-fa10fb4a1480","containerId":"53696c3e-110a-42fb-91fa-b84cd9f19107","name":"create-201","url":"{{apiUrl}}/credential","method":"POST","sortNum":10000,"created":"2022-07-15T20:15:07.945Z","modified":"2022-07-15T20:19:07.339Z","headers":[{"name":"Authorization","value":"Bearer {{token}}"}],"params":[],"body":{"type":"json","raw":"{\n  \"label\": \"{{lable}}\",\n  \"userName\": \"{{#enum, Paulo, Fernanda, Joanna}} {{#enum, Lago, Barros, Santos, Pinheiro}}\",\n  \"url\": \"{{#enum, http, https}}://{{#enum, globo, gmail, sites}}.com/{{#guid}}\",\n  \"password\": \"{{password}}\"\n}","form":[]},"tests":[{"type":"res-code","custom":"","action":"equal","value":"201"}]},{"_id":"bc860fba-dfa2-40e0-b3fb-f9514503d783","colId":"1e431bf5-dd3f-4be4-8d48-fa10fb4a1480","containerId":"369c9807-6ce9-4b19-abad-fc4037295331","name":"SETENV","url":"{{apiUrl}}/test","method":"POST","sortNum":10000,"created":"2022-07-15T20:15:07.946Z","modified":"2022-07-15T20:15:07.946Z","headers":[{"name":"Authorization","value":"Bearer {{token}}"}],"params":[],"body":{"type":"json","raw":"{\n  \"email\": \"{{#email}}\",\n  \"password\": \"{{#number, 10000,999999}}{{#number, 10000,999999}}\"\n}","form":[]},"tests":[{"type":"set-env-var","custom":"json.password","action":"setto","value":"{{password}}"},{"type":"set-env-var","custom":"json.email","action":"setto","value":"{{email}}"}]},{"_id":"cf7c4cdc-5f81-4464-9205-08d795a69173","colId":"1e431bf5-dd3f-4be4-8d48-fa10fb4a1480","containerId":"42f703fd-12d1-4ff1-8c0b-4a5f9b44b7ab","name":"getOne-200","url":"{{apiUrl}}/credential?id={{id}}","method":"GET","sortNum":10000,"created":"2022-07-15T20:15:07.947Z","modified":"2022-07-18T17:41:59.890Z","headers":[{"name":"Authorization","value":"Bearer {{token}}"}],"params":[{"name":"id","value":"{{id}}","isPath":false}],"tests":[{"type":"res-code","custom":"","action":"equal","value":"200"}]},{"_id":"868b9d02-3a1c-4e56-aef9-e9d1dfdf4857","colId":"1e431bf5-dd3f-4be4-8d48-fa10fb4a1480","containerId":"dcab6444-45f3-46e9-8749-4b17e3188706","name":"delete-204","url":"{{apiUrl}}/credential/{{id}}","method":"DELETE","sortNum":10000,"created":"2022-07-15T20:15:07.948Z","modified":"2022-07-15T20:20:58.768Z","headers":[{"name":"Authorization","value":"Bearer {{token}}"}],"params":[],"tests":[{"type":"res-code","custom":"","action":"equal","value":"204"}]},{"_id":"8875ce8b-3ca8-4a33-b234-f804ec6d9dc5","colId":"1e431bf5-dd3f-4be4-8d48-fa10fb4a1480","containerId":"be220905-a52e-4f8e-bdb1-f858367a7939","name":"SETENV","url":"{{apiUrl}}/test","method":"POST","sortNum":10000,"created":"2022-07-15T20:15:55.456Z","modified":"2022-07-18T12:37:05.396Z","headers":[{"name":"Authorization","value":"Bearer {{token}}"}],"params":[],"body":{"type":"json","raw":"{\n  \"id\": 1,\n  \"lable\": \"{{#string}}\"\n}","form":[]},"tests":[{"type":"set-env-var","custom":"json.id","action":"setto","value":"{{id}}"},{"type":"set-env-var","custom":"json.lable","action":"setto","value":"{{lable}}"}]},{"_id":"692bf1b7-2bf3-40b7-9739-c419204ba259","colId":"1e431bf5-dd3f-4be4-8d48-fa10fb4a1480","containerId":"2785ec35-c5af-4137-b505-a918e6fd0711","name":"SETENV","url":"{{apiUrl}}/test","method":"POST","sortNum":10000,"created":"2022-07-15T20:23:16.862Z","modified":"2022-07-15T20:23:16.862Z","headers":[{"name":"Authorization","value":"Bearer {{token}}"}],"params":[],"body":{"type":"json","raw":"{\n  \"id\": 1,\n  \"lable\": \"{{#string}}\"\n}","form":[]},"tests":[{"type":"set-env-var","custom":"json.id","action":"setto","value":"{{id}}"},{"type":"set-env-var","custom":"json.lable","action":"setto","value":"{{lable}}"}]},{"_id":"9c807dd0-594f-4a58-9b4d-8a1675e5425d","colId":"1e431bf5-dd3f-4be4-8d48-fa10fb4a1480","containerId":"3ad2ce09-9415-4bce-91c0-81461384e3f9","name":"create-201","url":"{{apiUrl}}/secure-note","method":"POST","sortNum":10000,"created":"2022-07-15T20:23:16.863Z","modified":"2022-07-16T03:48:07.806Z","headers":[{"name":"Authorization","value":"Bearer {{token}}"}],"params":[],"body":{"type":"json","raw":"{\n  \"title\": \"{{lable}}\",\n  \"bodyNote\": \"{{#string}} {{#string}} {{#string}} {{#string}} {{#string}}\"\n}","form":[]},"tests":[{"type":"res-code","custom":"","action":"equal","value":"201"}]},{"_id":"18c893ec-6b0f-4f0c-87bc-d394065c9669","colId":"1e431bf5-dd3f-4be4-8d48-fa10fb4a1480","containerId":"f5769f4d-65e2-4c8c-a66a-5d4b7e362a0e","name":"getOne-200","url":"{{apiUrl}}/secure-note?id={{id}}","method":"GET","sortNum":10000,"created":"2022-07-15T20:23:16.866Z","modified":"2022-07-18T17:34:25.897Z","headers":[{"name":"Authorization","value":"Bearer {{token}}"}],"params":[{"name":"id","value":"{{id}}","isPath":false}],"tests":[{"type":"res-code","custom":"","action":"equal","value":"200"}]},{"_id":"ad641930-4fb6-48ae-8497-b71624e3e56f","colId":"1e431bf5-dd3f-4be4-8d48-fa10fb4a1480","containerId":"12587671-fc1a-42eb-9a77-13a69c4893d8","name":"delete-204","url":"{{apiUrl}}/secure-note/{{id}}","method":"DELETE","sortNum":10000,"created":"2022-07-15T20:23:16.868Z","modified":"2022-07-15T20:25:23.209Z","headers":[{"name":"Authorization","value":"Bearer {{token}}"}],"params":[],"tests":[{"type":"res-code","custom":"","action":"equal","value":"204"}]},{"_id":"1efd75c7-e0c3-4320-b88c-ca72fd920fb3","colId":"1e431bf5-dd3f-4be4-8d48-fa10fb4a1480","containerId":"e015dd07-2069-4dde-a053-641aa9094b3f","name":"SETENV","url":"{{apiUrl}}/test","method":"POST","sortNum":10000,"created":"2022-07-18T11:13:54.538Z","modified":"2022-07-18T12:06:21.700Z","headers":[{"name":"Authorization","value":"Bearer {{token}}"}],"params":[],"body":{"type":"json","raw":"{\n  \"number\": \"{{#number, 1000, 9999}}{{#number, 1000, 9999}}{{#number, 1000, 9999}}{{#number, 0, 9}}\",\n  \"id\": 1,\n  \"password\": \"{{#number, 100000, 999999}}\",\n  \"lable\": \"{{#enum, MasterCard, Elo, Bradesco, Nubank, Brasil}}\"\n}","form":[]},"tests":[{"type":"set-env-var","custom":"json.id","action":"setto","value":"{{id}}"},{"type":"set-env-var","custom":"json.number","action":"setto","value":"{{number}}"},{"type":"set-env-var","custom":"json.lable","action":"setto","value":"{{lable}}"}]},{"_id":"25f00948-6226-4365-aff1-0bc4f0877415","colId":"1e431bf5-dd3f-4be4-8d48-fa10fb4a1480","containerId":"068d8990-a032-4d5e-bf2f-5883afec2bb4","name":"create-201","url":"{{apiUrl}}/card","method":"POST","sortNum":10000,"created":"2022-07-18T11:13:54.541Z","modified":"2022-07-18T11:51:10.709Z","headers":[{"name":"Authorization","value":"Bearer {{token}}"}],"params":[],"body":{"type":"json","raw":"{\n  \"number\": \"{{number}}\",\n  \"holderName\": \"{{#enum, Paulo, Fernanda, Joanna}} {{#enum, L, B, S, P}} {{#enum, Lago, Barros, Santos, Pinheiro}}\",\n  \"secureCode\": \"{{#number, 100, 999}}\",\n  \"password\": \"{{#number, 100000, 999999}}\",\n  \"lable\": \"{{lable}}\",\n  \"type\": \"{{#enum, credit, debit, both}}\",\n  \"expirationDate\": \"{{#number, 10, 12}}/{{#number, 10, 99}}\",\n  \"isVirtual\": true\n}","form":[]},"tests":[{"type":"res-code","custom":"","action":"equal","value":"201"}]},{"_id":"d1ad7fae-0898-4713-893e-a2752c2d180d","colId":"1e431bf5-dd3f-4be4-8d48-fa10fb4a1480","containerId":"8bbeeea9-f051-434a-ab2f-ef00c8999595","name":"getOne-200","url":"{{apiUrl}}/card?id={{id}}","method":"GET","sortNum":10000,"created":"2022-07-18T11:13:54.543Z","modified":"2022-07-18T12:00:14.152Z","headers":[{"name":"Authorization","value":"Bearer {{token}}"}],"params":[{"name":"id","value":"{{id}}","isPath":false}],"tests":[{"type":"res-code","custom":"","action":"equal","value":"200"}]},{"_id":"c421b976-0e4e-417d-9459-9f9f27944265","colId":"1e431bf5-dd3f-4be4-8d48-fa10fb4a1480","containerId":"f2e6b1f0-b0a0-47f5-bcd3-6eba666ebf1b","name":"delete-204","url":"{{apiUrl}}/card/{{id}}","method":"DELETE","sortNum":10000,"created":"2022-07-18T11:13:54.546Z","modified":"2022-07-18T12:16:36.815Z","headers":[{"name":"Authorization","value":"Bearer {{token}}"}],"params":[],"tests":[{"type":"res-code","custom":"","action":"equal","value":"204"}]},{"_id":"e3ca85ca-e667-4283-a87a-9f310809f8a2","colId":"1e431bf5-dd3f-4be4-8d48-fa10fb4a1480","containerId":"d52b560e-ae38-4ae6-bb1c-66e303974e5a","name":"SETENV","url":"{{apiUrl}}/test","method":"POST","sortNum":10000,"created":"2022-07-18T17:15:30.223Z","modified":"2022-07-18T17:15:30.223Z","headers":[{"name":"Authorization","value":"Bearer {{token}}"}],"params":[],"body":{"type":"json","raw":"{\n  \"id\": 1,\n  \"lable\": \"{{#string}}\"\n}","form":[]},"tests":[{"type":"set-env-var","custom":"json.id","action":"setto","value":"{{id}}"},{"type":"set-env-var","custom":"json.lable","action":"setto","value":"{{lable}}"}]},{"_id":"632de326-1c21-41c2-aa4e-f563cecb022d","colId":"1e431bf5-dd3f-4be4-8d48-fa10fb4a1480","containerId":"3532d702-468f-408f-ba91-84da5aded2a2","name":"create-201","url":"{{apiUrl}}/wi-fi","method":"POST","sortNum":10000,"created":"2022-07-18T17:15:30.224Z","modified":"2022-07-18T17:23:26.902Z","headers":[{"name":"Authorization","value":"Bearer {{token}}"}],"params":[],"body":{"type":"json","raw":"{\n  \"lable\": \"{{lable}}\",\n  \"name\": \"{{#string}}\",\n  \"password\": \"{{#number, 1000, 999999}}\"\n}","form":[]},"tests":[{"type":"res-code","custom":"","action":"equal","value":"201"}]},{"_id":"6cf44cba-3480-4a0c-9b03-615326ee9755","colId":"1e431bf5-dd3f-4be4-8d48-fa10fb4a1480","containerId":"bcf4a36b-349d-443f-ad51-c526e806732c","name":"getOne-200","url":"{{apiUrl}}/wi-fi?id={{id}}","method":"GET","sortNum":10000,"created":"2022-07-18T17:15:30.227Z","modified":"2022-07-18T17:35:29.024Z","headers":[{"name":"Authorization","value":"Bearer {{token}}"}],"params":[{"name":"id","value":"{{id}}","isPath":false}],"tests":[{"type":"res-code","custom":"","action":"equal","value":"200"}]},{"_id":"dfa3f884-a95c-495d-8013-c2eb8eb50e1d","colId":"1e431bf5-dd3f-4be4-8d48-fa10fb4a1480","containerId":"b50f57b4-d339-4589-b8d5-e8d9fc6f1913","name":"delete-204","url":"{{apiUrl}}/wi-fi/{{id}}","method":"DELETE","sortNum":10000,"created":"2022-07-18T17:15:30.229Z","modified":"2022-07-18T17:31:10.610Z","headers":[{"name":"Authorization","value":"Bearer {{token}}"}],"params":[],"tests":[{"type":"res-code","custom":"","action":"equal","value":"204"}]},{"_id":"535d3be2-56b9-45c5-a8dc-12fd6996ae23","colId":"1e431bf5-dd3f-4be4-8d48-fa10fb4a1480","containerId":"4d91744f-e457-434c-8db7-85f7769b71ad","name":"sign-up-409","url":"{{apiUrl}}/sign-up","method":"POST","sortNum":20000,"created":"2022-07-15T20:15:07.953Z","modified":"2022-07-15T20:15:07.953Z","headers":[],"params":[],"body":{"type":"json","raw":"{\n  \"email\": \"{{email}}\",\n  \"password\": \"{{password}}\"\n}","form":[]},"tests":[{"type":"res-code","custom":"","action":"equal","value":"409"}]},{"_id":"28377819-d37d-4751-814e-ea8bb44c4681","colId":"1e431bf5-dd3f-4be4-8d48-fa10fb4a1480","containerId":"b31ff388-50d7-497c-bb35-4a4f0d39ab6a","name":"sign-in-200","url":"{{apiUrl}}/sign-in","method":"POST","sortNum":20000,"created":"2022-07-15T20:15:07.954Z","modified":"2022-07-15T20:50:02.619Z","headers":[],"params":[],"body":{"type":"json","raw":"{\n  \"email\": \"{{email}}\",\n  \"password\": \"{{password}}\"\n}","form":[]},"tests":[{"type":"res-code","custom":"","action":"equal","value":"200"},{"type":"res-body","custom":"","action":"isjson","value":""},{"type":"set-env-var","custom":"json.token","action":"setto","value":"{{token}}"}]},{"_id":"c85bb08f-64e4-4169-9f6a-4ee23821bebb","colId":"1e431bf5-dd3f-4be4-8d48-fa10fb4a1480","containerId":"42f703fd-12d1-4ff1-8c0b-4a5f9b44b7ab","name":"getMany-200 ","url":"{{apiUrl}}/credential","method":"GET","sortNum":20000,"created":"2022-07-15T20:15:07.955Z","modified":"2022-07-15T20:53:45.274Z","headers":[{"name":"Authorization","value":"Bearer {{token}}"}],"params":[],"tests":[{"type":"res-code","custom":"","action":"equal","value":"200"}]},{"_id":"1db0f58c-c438-4f0e-9e34-3b2f2d829807","colId":"1e431bf5-dd3f-4be4-8d48-fa10fb4a1480","containerId":"53696c3e-110a-42fb-91fa-b84cd9f19107","name":"create-already-409","url":"{{apiUrl}}/credential","method":"POST","sortNum":20000,"created":"2022-07-15T20:19:17.160Z","modified":"2022-07-15T20:39:36.967Z","headers":[{"name":"Authorization","value":"Bearer {{token}}"}],"params":[],"body":{"type":"json","raw":"{\n  \"label\": \"{{lable}}\",\n  \"userName\": \"{{#enum, Paulo, Fernanda, Joanna}} {{#enum, Lago, Barros, Santos, Pinheiro}}\",\n  \"url\": \"{{#enum, http, https}}://{{#enum, globo, gmail, sites}}.com/{{#guid}}\",\n  \"password\": \"{{password}}\"\n}","form":[]},"tests":[{"type":"res-code","custom":"","action":"equal","value":"409"}]},{"_id":"337e6432-9e9d-4a37-ab44-bc9caff3af48","colId":"1e431bf5-dd3f-4be4-8d48-fa10fb4a1480","containerId":"3ad2ce09-9415-4bce-91c0-81461384e3f9","name":"create-already-409","url":"{{apiUrl}}/secure-note","method":"POST","sortNum":20000,"created":"2022-07-15T20:23:16.864Z","modified":"2022-07-18T17:33:49.686Z","headers":[{"name":"Authorization","value":"Bearer {{token}}"}],"params":[],"body":{"type":"json","raw":"{\n  \"title\": \"{{lable}}\",\n  \"bodyNote\": \"{{#string}} {{#string}} {{#string}} {{#string}} {{#string}}\"\n}","form":[]},"tests":[{"type":"res-code","custom":"","action":"equal","value":"409"}]},{"_id":"aec94e99-a4be-4ad1-a7f1-ef309abacf47","colId":"1e431bf5-dd3f-4be4-8d48-fa10fb4a1480","containerId":"f5769f4d-65e2-4c8c-a66a-5d4b7e362a0e","name":"getMany-200 ","url":"{{apiUrl}}/secure-note","method":"GET","sortNum":20000,"created":"2022-07-15T20:23:16.867Z","modified":"2022-07-18T17:35:08.117Z","headers":[{"name":"Authorization","value":"Bearer {{token}}"}],"params":[],"tests":[{"type":"res-code","custom":"","action":"equal","value":"200"}]},{"_id":"273a57a2-58a6-48ed-8b35-52b1630e2729","colId":"1e431bf5-dd3f-4be4-8d48-fa10fb4a1480","containerId":"068d8990-a032-4d5e-bf2f-5883afec2bb4","name":"create-already-409","url":"{{apiUrl}}/card","method":"POST","sortNum":20000,"created":"2022-07-18T11:13:54.542Z","modified":"2022-07-18T11:50:47.579Z","headers":[{"name":"Authorization","value":"Bearer {{token}}"}],"params":[],"body":{"type":"json","raw":"{\n  \"number\": \"{{number}}\",\n  \"holderName\": \"{{#enum, Paulo, Fernanda, Joanna}} {{#enum, L, B, S, P}} {{#enum, Lago, Barros, Santos, Pinheiro}}\",\n  \"secureCode\": \"{{#number, 100, 999}}\",\n  \"password\": \"{{#number, 100000, 999999}}\",\n  \"lable\": \"{{lable}}\",\n  \"type\": \"{{#enum, credit, debit, both}}\",\n  \"expirationDate\": \"{{#number, 10, 12}}/{{#number, 10, 99}}\",\n  \"isVirtual\": true\n}","form":[]},"tests":[{"type":"res-code","custom":"","action":"equal","value":"409"}]},{"_id":"892db2eb-7b5f-40ee-9795-7983f4b1274d","colId":"1e431bf5-dd3f-4be4-8d48-fa10fb4a1480","containerId":"8bbeeea9-f051-434a-ab2f-ef00c8999595","name":"getMany-200 ","url":"{{apiUrl}}/card","method":"GET","sortNum":20000,"created":"2022-07-18T11:13:54.544Z","modified":"2022-07-18T12:07:18.617Z","headers":[{"name":"Authorization","value":"Bearer {{token}}"}],"params":[],"tests":[{"type":"res-code","custom":"","action":"equal","value":"200"}]},{"_id":"625d550c-32c2-4b50-9875-93f4f91216f7","colId":"1e431bf5-dd3f-4be4-8d48-fa10fb4a1480","containerId":"bcf4a36b-349d-443f-ad51-c526e806732c","name":"getMany-200 ","url":"{{apiUrl}}/wi-fi","method":"GET","sortNum":20000,"created":"2022-07-18T17:15:30.228Z","modified":"2022-07-18T17:35:44.983Z","headers":[{"name":"Authorization","value":"Bearer {{token}}"}],"params":[],"tests":[{"type":"res-code","custom":"","action":"equal","value":"200"}]},{"_id":"13528406-4aac-4768-be0e-65a38652bdfd","colId":"1e431bf5-dd3f-4be4-8d48-fa10fb4a1480","containerId":"4d91744f-e457-434c-8db7-85f7769b71ad","name":"sign-up-422","url":"{{apiUrl}}/sign-up","method":"POST","sortNum":30000,"created":"2022-07-15T20:15:07.959Z","modified":"2022-07-15T20:15:07.959Z","headers":[],"params":[],"body":{"type":"json","raw":"{\n  \"email\": \"{{email}}\",\n  \"password\": \"546484\"\n}","form":[]},"tests":[{"type":"res-code","custom":"","action":"equal","value":"422"}]},{"_id":"162f9056-eb5c-4faa-8320-7c4d131ea567","colId":"1e431bf5-dd3f-4be4-8d48-fa10fb4a1480","containerId":"b31ff388-50d7-497c-bb35-4a4f0d39ab6a","name":"sign-in-422","url":"{{apiUrl}}/sign-in","method":"POST","sortNum":30000,"created":"2022-07-15T20:15:07.960Z","modified":"2022-07-15T20:15:07.960Z","headers":[],"params":[],"body":{"type":"json","raw":"{\n  \"email\": \"{{email}}\",\n  \"passwor\": \"{{password}}\"\n}","form":[]},"tests":[{"type":"res-code","custom":"","action":"equal","value":"422"},{"type":"res-body","custom":"","action":"isjson","value":""}]},{"_id":"72e619a7-5de9-495d-ab51-c5249227ff2a","colId":"1e431bf5-dd3f-4be4-8d48-fa10fb4a1480","containerId":"b31ff388-50d7-497c-bb35-4a4f0d39ab6a","name":"sign-in-401","url":"{{apiUrl}}/sign-in","method":"POST","sortNum":40000,"created":"2022-07-15T20:15:07.961Z","modified":"2022-07-15T20:15:07.961Z","headers":[],"params":[],"body":{"type":"json","raw":"{\n  \"email\": \"cc{{email}}\",\n  \"password\": \"{{password}}\"\n}","form":[]},"tests":[{"type":"res-code","custom":"","action":"equal","value":"401"},{"type":"res-body","custom":"","action":"isjson","value":""}]}]}
